MANIFEST.in
README.rst
setup.py
pytabgeo/__init__.py
pytabgeo/pytabgeo.py
pytabgeo/tabgeo_country_v4.dat
pytabgeo.egg-info/PKG-INFO
pytabgeo.egg-info/SOURCES.txt
pytabgeo.egg-info/dependency_links.txt
pytabgeo.egg-info/entry_points.txt
pytabgeo.egg-info/top_level.txt