Metadata-Version: 1.1
Name: pytabgeo
Version: 0.2
Summary: Python driver for TabGeo.com base
Home-page: https://github.com/axce1/pytabgeo
Author: axce1
Author-email: axce1.github@gmail.com
License: WTFPL
Platform: any
Classifier: Programming Language :: Python :: 2
Classifier: Programming Language :: Python :: 2.7
Classifier: Programming Language :: Python :: 3
Classifier: Programming Language :: Python :: 3.3
Classifier: Programming Language :: Python :: 3.4
